MANIFEST.in
README.rst
setup.py
bonzo/__init__.py
bonzo/server.py
bonzo/testing.py
bonzo.egg-info/PKG-INFO
bonzo.egg-info/SOURCES.txt
bonzo.egg-info/dependency_links.txt
bonzo.egg-info/requires.txt
bonzo.egg-info/top_level.txt