Metadata-Version: 1.1
Name: bonzo
Version: 0.1.2
Summary: Bonzo is a minimalistic SMTP Proxy built on top of Tornado.
Home-page: https://github.com/puentesarrin/bonzo
Author: Jorge Puente Sarrín
Author-email: puentesarrin@gmail.com
License: Apache License, Version 2.0
Keywords: bonzo,tornado,smtp,proxy
Platform: UNKNOWN
Classifier: Development Status :: 4 - Beta
Classifier: Intended Audience :: Developers
Classifier: License :: OSI Approved :: Apache Software License
Classifier: Operating System :: OS Independent
Classifier: Programming Language :: Python
Classifier: Programming Language :: Python :: 2
Classifier: Programming Language :: Python :: 2.6
Classifier: Programming Language :: Python :: 2.7
Classifier: Programming Language :: Python :: 3
Classifier: Programming Language :: Python :: 3.2
Classifier: Programming Language :: Python :: 3.3
Classifier: Programming Language :: Python :: 3.4
Classifier: Programming Language :: Python :: Implementation :: CPython
Classifier: Programming Language :: Python :: Implementation :: PyPy
Classifier: Topic :: Internet :: Proxy Servers
